{
  "rho_crit": 6.0,
  "scenarios": {
    "recall_1.0": {
      "recall": 1.0,
      "crush_onset_s": 20.65000000000016,
      "density_only_lead_s": 4.2,
      "multimodal_lead_s": 5.6
    },
    "recall_0.51": {
      "recall": 0.51,
      "crush_onset_s": 20.65000000000016,
      "density_only_lead_s": 4.4,
      "multimodal_lead_s": 5.2
    },
    "recall_0.3": {
      "recall": 0.3,
      "crush_onset_s": 20.65000000000016,
      "density_only_lead_s": 4.4,
      "multimodal_lead_s": 6.0
    }
  }
}